{
  "basePath": "/",
  "host": "47.108.135.148:16700",
  "info": {
    "description": "服务名: masterdata-service",
    "version": "1.0",
    "title": "普朗克主数据服务(masterdata-service) API接口"
  },
  "swagger": "2.0",
  "paths": {
    "/masterdata-service/storageTakeCheckTask/compareTakeCheckSerialNos": {
      "post": {
        "tags": [
          "仓库盘点任务相关"
        ],
        "summary": "比较盘点序列号",
        "operationId": "compareTakeCheckSerialNosUsingPOST",
        "consumes": [
          "application/json"
        ],
        "produces": [
          "*/*"
        ],
        "parameters": [
          {
            "in": "body",
            "name": "compareRequest",
            "description": "compareRequest",
            "required": true,
            "schema": {
              "originalRef": "盘点序列号比较请求DTO",
              "$ref": "#/definitions/盘点序列号比较请求DTO"
            }
          }
        ],
        "responses": {
          "200": {
            "description": "OK",
            "schema": {
              "originalRef": "JSONResult«盘点序列号比较结果DTO»",
              "$ref": "#/definitions/JSONResult«盘点序列号比较结果DTO»"
            }
          },
          "201": {
            "description": "Created"
          },
          "401": {
            "description": "Unauthorized"
          },
          "403": {
            "description": "Forbidden"
          },
          "404": {
            "description": "Not Found"
          }
        },
        "deprecated": false,
        "x-order": "130"
      }
    }
  },
  "definitions": {
    "盘点序列号比较请求DTO": {
      "type": "object",
      "required": [
        "materialId",
        "warehouseId"
      ],
      "properties": {
        "warehouseId": {
          "type": "integer",
          "format": "int64",
          "description": "仓位id"
        },
        "materialId": {
          "type": "integer",
          "format": "int64",
          "description": "物料id"
        },
        "lotNo": {
          "type": "string",
          "description": "批次号"
        },
        "serialNos": {
          "type": "array",
          "description": "序列号集合",
          "items": {
            "originalRef": "盘点任务盘点明细序列号DTO_1",
            "$ref": "#/definitions/盘点任务盘点明细序列号DTO_1"
          }
        }
      },
      "title": "盘点序列号比较请求DTO"
    },
    "JSONResult«盘点序列号比较结果DTO»": {
      "type": "object",
      "properties": {
        "code": {
          "type": "integer",
          "format": "int32",
          "example": 0,
          "description": "返回码"
        },
        "msg": {
          "type": "string",
          "example": "服务器异常",
          "description": "返回消息说明"
        },
        "data": {
          "description": "响应结果",
          "originalRef": "盘点序列号比较结果DTO",
          "$ref": "#/definitions/盘点序列号比较结果DTO"
        },
        "ts": {
          "type": "integer",
          "format": "int64",
          "example": 1356019200000,
          "description": "服务器结果返回时的 Unix timestamp,单位毫秒"
        }
      },
      "title": "JSONResult«盘点序列号比较结果DTO»"
    }
  }
}